{
    "nodeMenuItems": [
        {
            "name": "Back",
            "color": "white",
            "texture": "SecondIcon",
            "subNodeMenu": [
                {
                    "actionName": "Hack2",
                    "actionValue": "Gather Info"
                },
                {
                    "actionName": "Hack2",
                    "actionValue": "Gather Info"
                },

                {
                    "actionName": "Hack2",
                    "actionValue": "Gather Info"
                },
                {
                    "actionName": "Hack2",
                    "actionValue": "Gather Info"
                }
            ]
        },
        {
            "name": "Investigate",
            "color": "blue",
            "texture": "SecondIcon",
            "subNodeMenu": [
                {
                    "actionName": "Hack2",
                    "actionValue": "Gather Info"
                },
                {
                    "actionName": "Hack2",
                    "actionValue": "Gather Info"
                },

                {
                    "actionName": "Hack2",
                    "actionValue": "Gather Info"
                },
                {
                    "actionName": "Hack2",
                    "actionValue": "Gather Info"
                }
            ]
        },
        {
            "name": "Mitigate",
            "color": "green",
            "texture": "ThirdIcon",
            "subNodeMenu": [
                {
                    "actionName": "Hack2",
                    "actionValue": "Gather Info"
                },
                {
                    "actionName": "Hack2",
                    "actionValue": "Gather Info"
                },

                {
                    "actionName": "Hack2",
                    "actionValue": "Gather Info"
                },
                {
                    "actionName": "Hack2",
                    "actionValue": "Gather Info"
                }
            ]
        },
        {
            "name": "Home",
            "color": "white",
            "texture": "SecondIcon",
            "subNodeMenu": [
                {
                    "actionName": "Hack2",
                    "actionValue": "Gather Info"
                },
                {
                    "actionName": "Hack2",
                    "actionValue": "Gather Info"
                },

                {
                    "actionName": "Hack2",
                    "actionValue": "Gather Info"
                },
                {
                    "actionName": "Hack2",
                    "actionValue": "Gather Info"
                }
            ]
        },
        {
            "name": "Report",
            "color": "yellow",
            "texture": "ForthIcon",
            "subNodeMenu": [
                {
                    "actionName": "Hack2",
                    "actionValue": "Gather Info"
                },
                {
                    "actionName": "Hack2",
                    "actionValue": "Gather Info"
                },

                {
                    "actionName": "Hack2",
                    "actionValue": "Gather Info"
                },
                {
                    "actionName": "Hack2",
                    "actionValue": "Gather Info"
                }
            ]
        },
        {
            "name": "Enrich",
            "color": "red",
            "texture": "FirstIcon",
            "subNodeMenu": [
                {
                    "actionName": "Expand",
                    "actionValue": "Gather Info"
                },
                {
                    "actionName": "Hack2",
                    "actionValue": "Gather Info"
                },

                {
                    "actionName": "Hack2",
                    "actionValue": "Gather Info"
                },
                {
                    "actionName": "Hack2",
                    "actionValue": "Gather Info"
                }
            ]
        }
    ]
}
